pandas_sanddance/__init__.py
pandas_sanddance/_frontend.py
pandas_sanddance/_version.py
pandas_sanddance/sanddance.py
pandas_sanddance/labextension/pandas-sanddance-0.2.0.tgz
pandas_sanddance/nbextension/__init__.py
pandas_sanddance/nbextension/static/extension.js
pandas_sanddance/nbextension/static/index.js
pandas_sanddance/nbextension/static/index.js.map
pandas_sanddance/tests/__init__.py
pandas_sanddance/tests/conftest.py
pandas_sanddance/tests/test_example.py
pandas_sanddance/tests/test_nbextension_path.py
pandas_sanddance-0.2.0.data/data/etc/jupyter/nbconfig/notebook.d/pandas_sanddance.json
pandas_sanddance-0.2.0.data/data/share/jupyter/lab/extensions/pandas-sanddance-0.2.0.tgz
pandas_sanddance-0.2.0.data/data/share/jupyter/nbextensions/pandas_sanddance/extension.js
pandas_sanddance-0.2.0.data/data/share/jupyter/nbextensions/pandas_sanddance/index.js
pandas_sanddance-0.2.0.data/data/share/jupyter/nbextensions/pandas_sanddance/index.js.map
pandas_sanddance-0.2.0.dist-info/LICENSE.txt
pandas_sanddance-0.2.0.dist-info/METADATA
pandas_sanddance-0.2.0.dist-info/WHEEL
pandas_sanddance-0.2.0.dist-info/top_level.txt
pandas_sanddance-0.2.0.dist-info/RECORD
